shelllnk/__init__.py
shelllnk/main.py
shelllnk/parser.py
shelllnk-1.0.0.dist-info/LICENSE
shelllnk-1.0.0.dist-info/METADATA
shelllnk-1.0.0.dist-info/WHEEL
shelllnk-1.0.0.dist-info/entry_points.txt
shelllnk-1.0.0.dist-info/top_level.txt
shelllnk-1.0.0.dist-info/RECORD
