Metadata-Version: 2.1
Name: shelllnk
Version: 1.0.0
Summary: Package for parsing Microsoft Shell Link (.lnk) files
Home-page: https://github.com/leekamentsky/shelllnk
Author: Lee Kamentsky
License: MIT
Platform: UNKNOWN
Classifier: License :: OSI Approved :: MIT License
Classifier: Operating System :: OS Independent
Classifier: Development Status :: 5 - Production/Stable
Classifier: Programming Language :: Python :: 3
